{
  "coc.preferences.formatOnSaveFiletypes": ["*"],
  "languageserver": {
    "javascript": {
      "command": "http-server",
      "rootPatterns": ["main.js"],
      "trace.server": "verbose",
      "filetypes": ["js"]
    },
    "ccls": {
            "command": "ccls",
            "filetypes": [
                "c",
                "cpp",
                "objc",
                "objcpp"
            ],
            "rootPatterns": [
                ".ccls",
                "compile_commands.json",
                ".vim/",
                ".git/",
                ".hg/"
            ],
            "initializationOptions": {
                "cache": {
                    "directory": "/tmp/ccls"
                },
                "highlight": { 
                    "lsRanges" : true
                },
                "index": {
                    "onChange": true
                },
                "highlight": {
                    "lsRanges" : true 
                }
            }
        }
    }
}
